{
  "1960s": {
    "NYK": {
      "Richie Guerin": 15.52,
      "Willie Naulls": 16.6,
      "Willis Reed": 15.88,
      "Dick Barnett": 10.38,
      "Walt Bellamy": 15.85,
      "Dave DeBusschere": 14,
      "Jim Barnes": 11.81,
      "Bob Boozer": 10.78,
      "Cazzie Russell": 9.04,
      "Dick Garmaker": 9.38,
      "Kenny Sears": 11.48,
      "Walt Frazier": 11.47,
      "Johnny Green": 11.51,
      "Dick Van Arsdale": 9.48,
      "Dave Stallworth": 9.33,
      "Phil Jordon": 9.58,
      "Howard Komives": 8.47,
      "Gene Shue": 7.47,
      "Len Chappell": 8.14,
      "Carl Braun": 8.45,
      "Art Heyman": 7.25,
      "Charlie Tyra": 8.92,
      "Bill Bradley": 8.06,
      "Al Butler": 7.14,
      "Johnny Egan": 7.45,
      "Bevo Nordmann": 8.59,
      "Jack George": 6.63,
      "Tom Gola": 7.74,
      "Paul Hogue": 7.67,
      "Mike Farmer": 6.32,
      "Dave Budd": 5.7,
      "Gene Conley": 6.1,
      "Jim Palmer": 5.23,
      "Phil Jackson": 5.55,
      "John Rudometkin": 4.23,
      "Cleveland Buckner": 4.48,
      "Em Bryant": 5.12,
      "Bob McNeill": 4.93,
      "Phil Rollins": 4.79,
      "Freddie Crawford": 4.19,
      "Barry Clemens": 4,
      "Darrall Imhoff": 5.77,
      "Donnie Butcher": 4.26,
      "Whitey Bell": 4.28,
      "Sam Stith": 3.64,
      "Don May": 3.32,
      "Bob Anderegg": 3.17,
      "Tom Hoover": 4.44,
      "Henry Akin": 3.02,
      "Whitey Martin": 3.64,
      "George Blaney": 2.53,
      "Neil Johnson": 3.06,
      "Nate Bowman": 3.22,
      "Bill Hosket": 2.26,
      "Mike Riordan": 2
    }
  }
}