{
  "2000s": {
    "ORL": {
      "Tracy McGrady": 20.57,
      "Steve Francis": 16.02,
      "Rashard Lewis": 13.25,
      "Dwight Howard": 18.46,
      "Juwan Howard": 12.54,
      "Grant Hill": 12.46,
      "Cuttino Mobley": 10.08,
      "Hedo Türkoğlu": 11.91,
      "Ron Mercer": 10.4,
      "Mike Miller": 10.33,
      "Darrell Armstrong": 12.93,
      "Chris Gatling": 10.71,
      "Jameer Nelson": 10.23,
      "Tariq Abdul-Wahad": 10.24,
      "Rafer Alston": 11.48,
      "Drew Gooden": 11.27,
      "Gordan Giriček": 9.14,
      "DeShawn Stevenson": 7.24,
      "Chucky Atkins": 7.22,
      "Mickaël Piétrus": 7.29,
      "Tyronn Lue": 7.85,
      "Maurice Evans": 6.55,
      "John Amaechi": 6.93,
      "Corey Maggette": 6.51,
      "Courtney Lee": 6.57,
      "Keyon Dooling": 5.94,
      "Troy Hudson": 6.43,
      "Carlos Arroyo": 6.41,
      "Darko Miličić": 10.11,
      "Horace Grant": 9.04,
      "Pat Garrity": 5.57,
      "Trevor Ariza": 7.06,
      "Monty Williams": 6.2,
      "Keith Bogans": 5.83,
      "Rod Strickland": 7.45,
      "Shawn Kemp": 7.77,
      "Michael Doleac": 6.44,
      "Kelvin Cato": 8.3,
      "Patrick Ewing": 6.19,
      "Tony Battie": 6.87,
      "Jacque Vaughn": 5.75,
      "Doug Christie": 7.49,
      "Bo Outlaw": 9.54,
      "Anthony Johnson": 4.96,
      "Shammond Williams": 4.22,
      "Ben Wallace": 10.61,
      "Brian Cook": 3.44,
      "Pat Burke": 4.14,
      "Donnell Harvey": 4.64,
      "Travis Diener": 2.78,
      "Marcin Gortat": 5.55,
      "Andrew DeClercq": 5.33,
      "Steven Hunter": 4.47,
      "Chris Whitney": 3.06,
      "Zaza Pachulia": 3.79,
      "Don Reid": 4.61,
      "Brandon Hunter": 2.85,
      "Sean Rooks": 3.89,
      "Stacey Augmon": 3.1,
      "Mario Kasun": 3.09,
      "Derek Strong": 2.88,
      "Jeryl Sasser": 3.85,
      "Cory Alexander": 2.93,
      "Adonal Foyle": 3.28,
      "Jud Buechler": 2.53,
      "Reece Gaines": 2.44,
      "Ryan Humphrey": 2.82,
      "Terence Morris": 2.37,
      "Olumide Oyedeji": 2
    }
  }
}