{
  "2020s": {
    "MIN": {
      "Anthony Edwards": 16.62,
      "Karl-Anthony Towns": 18.19,
      "Julius Randle": 15.33,
      "D'Angelo Russell": 14.01,
      "Malik Beasley": 10,
      "Ayo Dosunmu": 10.8,
      "Rudy Gobert": 15.64,
      "Naz Reid": 10.33,
      "Donte DiVincenzo": 10.69,
      "Jaden McDaniels": 9.75,
      "Jaylen Nowell": 6.71,
      "Patrick Beverley": 11.39,
      "Mike Conley": 9.29,
      "Ricky Rubio": 10.86,
      "Taurean Prince": 6.32,
      "Nickeil Alexander-Walker": 6.89,
      "Kyle Anderson": 9.8,
      "Bones Hyland": 5.78,
      "Juancho Hernangomez": 5.86,
      "Jarred Vanderbilt": 9.4,
      "Greg Monroe": 7.42,
      "Jarrett Culver": 5.18,
      "Monte Morris": 5.27,
      "Austin Rivers": 4.29,
      "Terrence Shannon Jr.": 3.41,
      "Luka Garza": 3.21,
      "Zyon Pullin": 3.31,
      "Rob Dillingham": 3.9,
      "Josh Okogie": 4.45,
      "Jordan McLaughlin": 5.38,
      "Jaylen Clark": 3.87,
      "Joan Beringer": 4.21,
      "Jake Layman": 3.14,
      "T.J. Warren": 3.61,
      "Nathan Knight": 3.2,
      "Bryn Forbes": 2.56,
      "Matt Ryan": 2.14,
      "Enrique Freeman": 4.8,
      "Julian Phillips": 2.5,
      "Rocco Zikarsky": 4.41,
      "Josh Minott": 2.51,
      "Ed Davis": 5.93,
      "Johnny Juzang": 1.47,
      "Leonard Miller": 1.67,
      "Leandro Bolmaro": 1.82,
      "Joe Ingles": 1.9,
      "Daishen Nix": 1.42,
      "McKinley Wright IV": 0.72,
      "Wendell Moore Jr.": 1.36,
      "PJ Dozier": 1.13,
      "Tristen Newton": 0.75,
      "Justin Jackson": 0,
      "Ashton Hagans": 0,
      "Jesse Edwards": 0.32
    }
  }
}